phonolammps/__init__.py
phonolammps/arrange.py
phonolammps/capture.py
phonolammps/iofile.py
phonolammps/phonopy_link.py
phonolammps/swissparam.py
phonolammps-0.10.1.data/scripts/phonolammps
phonolammps-0.10.1.dist-info/licenses/LICENSE
phonolammps-0.10.1.dist-info/METADATA
phonolammps-0.10.1.dist-info/WHEEL
phonolammps-0.10.1.dist-info/top_level.txt
phonolammps-0.10.1.dist-info/RECORD
