Metadata-Version: 2.4
Name: phonoLAMMPS
Version: 0.10.1
Summary: phonoLAMMPS module
Home-page: https://github.com/abelcarreras/phonolammps
Author: Abel Carreras
Author-email: abelcarreras83@gmail.com
License: MIT License
License-File: LICENSE
Requires-Dist: phonopy
Requires-Dist: numpy
Requires-Dist: matplotlib
Requires-Dist: seekpath
Requires-Dist: dynaphopy
Dynamic: author
Dynamic: author-email
Dynamic: description
Dynamic: description-content-type
Dynamic: home-page
Dynamic: license
Dynamic: license-file
Dynamic: requires-dist
Dynamic: summary
